Metadata-Version: 1.0
Name: machine-learning-support
Version: 0.0.2
Summary: This package contais some functions that support any data scientist to make operations on any dataframe easily
Home-page: UNKNOWN
Author: Mohab Youssef
Author-email: mohabyoussef09@gmail.com
License: UNKNOWN
Platform: UNKNOWN
